kafka_smart_producer/__init__.py
kafka_smart_producer/async_partition_health_monitor.py
kafka_smart_producer/async_producer.py
kafka_smart_producer/caching.py
kafka_smart_producer/exceptions.py
kafka_smart_producer/factories.py
kafka_smart_producer/health_config.py
kafka_smart_producer/health_mode.py
kafka_smart_producer/health_utils.py
kafka_smart_producer/lag_collector.py
kafka_smart_producer/partition_health_monitor.py
kafka_smart_producer/producer_config.py
kafka_smart_producer/producer_utils.py
kafka_smart_producer/protocols.py
kafka_smart_producer/sync_producer.py
kafka_smart_producer/threading.py
kafka_smart_producer-0.0.1.dist-info/METADATA
kafka_smart_producer-0.0.1.dist-info/WHEEL
kafka_smart_producer-0.0.1.dist-info/licenses/LICENSE
kafka_smart_producer-0.0.1.dist-info/RECORD
