Metadata-Version: 2.4
Name: kafka-smart-producer
Version: 0.0.1
Summary: Intelligent Kafka producer with real-time, lag-aware partition selection
Project-URL: Homepage, https://github.com/namphv/kafka-smart-producer
Project-URL: Repository, https://github.com/namphv/kafka-smart-producer
Project-URL: Issues, https://github.com/namphv/kafka-smart-producer/issues
Author-email: Pham Nam <namph.data@gmail.com>
License-File: LICENSE
Keywords: consumer-lag,kafka,partition-selection,producer,smart-routing
Classifier: Development Status :: 3 - Alpha
Classifier: Intended Audience :: Developers
Classifier: License :: OSI Approved :: MIT License
Classifier: Programming Language :: Python :: 3
Classifier: Programming Language :: Python :: 3.9
Classifier: Programming Language :: Python :: 3.10
Classifier: Programming Language :: Python :: 3.11
Classifier: Programming Language :: Python :: 3.12
Classifier: Topic :: Software Development :: Libraries :: Python Modules
Classifier: Topic :: System :: Distributed Computing
Requires-Python: >=3.9
Requires-Dist: cachetools>=5.0.0
Requires-Dist: confluent-kafka>=2.0.0
Requires-Dist: redis>=6.1.1
Provides-Extra: dev
Requires-Dist: black>=23.0.0; extra == 'dev'
Requires-Dist: mypy>=1.0.0; extra == 'dev'
Requires-Dist: pre-commit>=3.0.0; extra == 'dev'
Requires-Dist: pytest-asyncio>=0.21.0; extra == 'dev'
Requires-Dist: pytest>=7.0.0; extra == 'dev'
Requires-Dist: ruff>=0.1.0; extra == 'dev'
Provides-Extra: redis
Requires-Dist: redis>=4.0.0; extra == 'redis'
